django_postgres_partition-0.1.4.dist-info/licenses/LICENSE
psql_partition/__init__.py
psql_partition/apps.py
psql_partition/compiler.py
psql_partition/expressions.py
psql_partition/lookups.py
psql_partition/query.py
psql_partition/settings.py
psql_partition/sql.py
psql_partition/type_assertions.py
psql_partition/types.py
psql_partition/backend/__init__.py
psql_partition/backend/base.py
psql_partition/backend/base_impl.py
psql_partition/backend/introspection.py
psql_partition/backend/operations.py
psql_partition/backend/schema.py
psql_partition/backend/migrations/__init__.py
psql_partition/backend/migrations/patched_autodetector.py
psql_partition/backend/migrations/patched_migrations.py
psql_partition/backend/migrations/patched_project_state.py
psql_partition/backend/migrations/operations/__init__.py
psql_partition/backend/migrations/operations/add_default_partition.py
psql_partition/backend/migrations/operations/add_hash_partition.py
psql_partition/backend/migrations/operations/add_list_partition.py
psql_partition/backend/migrations/operations/add_range_partition.py
psql_partition/backend/migrations/operations/apply_state.py
psql_partition/backend/migrations/operations/create_materialized_view_model.py
psql_partition/backend/migrations/operations/create_partitioned_model.py
psql_partition/backend/migrations/operations/create_view_model.py
psql_partition/backend/migrations/operations/delete_default_partition.py
psql_partition/backend/migrations/operations/delete_hash_partition.py
psql_partition/backend/migrations/operations/delete_list_partition.py
psql_partition/backend/migrations/operations/delete_materialized_view_model.py
psql_partition/backend/migrations/operations/delete_partition.py
psql_partition/backend/migrations/operations/delete_partitioned_model.py
psql_partition/backend/migrations/operations/delete_range_partition.py
psql_partition/backend/migrations/operations/delete_view_model.py
psql_partition/backend/migrations/operations/partition.py
psql_partition/backend/migrations/state/__init__.py
django_postgres_partition-0.1.4.dist-info/METADATA
django_postgres_partition-0.1.4.dist-info/WHEEL
django_postgres_partition-0.1.4.dist-info/top_level.txt
django_postgres_partition-0.1.4.dist-info/RECORD
