Metadata-Version: 2.4
Name: django-postgres-partition
Version: 0.1.4
Summary: Partition support for django, based on django-postgres-extra
License-Expression: MIT
Project-URL: Homepage, https://gitlab.com/burke-software/django-postgres-partition
Keywords: django,postgres,postgresql,partitioning,partition,database,psqlextra
Classifier: Development Status :: 3 - Alpha
Classifier: Framework :: Django
Classifier: Framework :: Django :: 5.2
Classifier: Intended Audience :: Developers
Classifier: Operating System :: OS Independent
Classifier: Programming Language :: Python
Classifier: Programming Language :: Python :: 3
Classifier: Topic :: Database
Requires-Python: >=3.11
License-File: LICENSE
Requires-Dist: django>=5.2
Requires-Dist: psycopg>=3.2.6
Requires-Dist: python-dateutil>=2.9.0.post0
Dynamic: license-file
